MANIFEST.in
requirements.txt
setup.py
capysule/__init__.py
capysule/client.py
capysule/collection.py
capysule/tests.py
capysule/util.py
capysule.egg-info/PKG-INFO
capysule.egg-info/SOURCES.txt
capysule.egg-info/dependency_links.txt
capysule.egg-info/requires.txt
capysule.egg-info/top_level.txt
capysule/resources/__init__.py
capysule/resources/cases.py
capysule/resources/custom_fields.py
capysule/resources/history.py
capysule/resources/parties.py
capysule/resources/tags.py
capysule/resources/tests/__init__.py
capysule/resources/tests/test_parties.py