Metadata-Version: 1.1
Name: capysule
Version: 0.5.1
Summary: Bindings for Capsule CRM based on Requests and Booby
Home-page: https://github.com/bodylabs/capysule
Author: Body Labs
Author-email: paul.melnikow@bodylabs.com
License: Apache 2
Platform: UNKNOWN
Classifier: Development Status :: 2 - Pre-Alpha
Classifier: Intended Audience :: Developers
Classifier: License :: OSI Approved :: Apache Software License
Classifier: Operating System :: OS Independent
Classifier: Programming Language :: Python
Classifier: Topic :: Software Development :: Libraries :: Python Modules
